LICENCE
MANIFEST.in
README.md
README.rst
setup.py
django_stream.egg-info/PKG-INFO
django_stream.egg-info/SOURCES.txt
django_stream.egg-info/dependency_links.txt
django_stream.egg-info/not-zip-safe
django_stream.egg-info/top_level.txt
stream/__init__.py
stream/admin.py
stream/models.py
stream/registry.py
stream/signals.py
stream/tests.py
stream/utils.py
stream/templates/stream/action.html
stream/templatetags/__init__.py
stream/templatetags/stream_tags.py