Metadata-Version: 1.0
Name: django-stream
Version: 0.2.4
Summary: Activity stream application for Django
Home-page: https://github.com/caffeinehit/django-stream
Author: Alen Mujezinovic
Author-email: alen@caffeinehit.com
License: UNKNOWN
Platform: UNKNOWN
